{
  "schema_version": "1.0.0",
  "checkpoint_id": "secure-hybrid-hub-phase-8-guided-remediation",
  "system_id": "secure-hybrid-hub",
  "phase": "phase-8-guided-remediation",
  "state": "completed",
  "created_at": "2026-07-17T03:10:00+06:00",
  "actor": "codex-primary",
  "classification": "R1",
  "effective_policy_layers": ["managed/global", "system", "task", "workspace", "guided-plan", "research", "quality", "modifier"],
  "effective_policy_hash": "c29a5fdd4a66cbd411ae7429c10a02e1e70fb1cbf0336eb5a383b9dbb98b33ef",
  "delivered": [
    "broker-validated high-model work packets",
    "per-repository context and write maps",
    "exact file deliverables with file-specific instructions",
    "research-cache and official-source provenance handoff",
    "raw web content withheld from local coding prompts",
    "one broker-selected file per local inference",
    "bounded local loopback HTTP bridge with output token and stop limits",
    "sanitized compiler and test diagnostics in repair prompts",
    "per-packet dossier checkpoints and deterministic quality gates"
  ],
  "evidence": [
    "tests/test_guided.py",
    "tests/test_integration.py",
    "verification/guided-orchestration.json",
    "verification/gemma3-guided-evaluation.json"
  ],
  "unresolved_risks": [
    "gemma3:1b failed the first guided packet after four deterministic attempts",
    "live cloud diagnosis/review remains disabled until a project-specific approved provider route exists",
    "SearXNG discovery remains uninstalled and requires separate service approval",
    "No model or test suite guarantees perfect code; independent review and client-specific operated controls remain required"
  ],
  "next_allowed_phase": "authorized-model-capability-evaluation-or-low-risk-pilot"
}
